contradict/__init__.py
contradict/error.py
contradict/hashmap.py
contradict/sorted_dict.py
coppr/__init__.py
coppr/error.py
coppr/hashmap.py
coppr/sorted_dict.py
coppr/trie.py
contradict-2.0.1.dist-info/METADATA
contradict-2.0.1.dist-info/WHEEL
contradict-2.0.1.dist-info/top_level.txt
contradict-2.0.1.dist-info/RECORD
