Metadata-Version: 2.1
Name: contradict
Version: 2.0.1
Summary: A thread safe implementation of the SortedDict.
Home-page: https://github.com/soumasish/contradict
Author: Soumasish Goswami
Author-email: hello@soumasish.io
License: MIT
Platform: UNKNOWN
Classifier: License :: OSI Approved :: MIT License
Classifier: Programming Language :: Python :: 3
Classifier: Programming Language :: Python :: 3.7
Requires-Dist: hipster
Requires-Dist: readerwriterlock
